new_sigproextractor/__init__.py
new_sigproextractor/sigpro.py
new_sigproextractor/subroutines.py
new_sigproextractor/version.py
sigproextractor/__init__.py
sigproextractor/sigpro.py
sigproextractor/subroutines.py
sigproextractor/version.py
sigproextractor/data/21_breast_WGS_substitutions.mat
sigproextractor/data/all_mice_silvio.txt
sigproextractor/data/csvexample.csv
sigproextractor/data/sigProfiler_DBS_signatures.csv
sigproextractor/data/sigProfiler_ID_signatures.csv
sigproextractor/data/sigProfiler_SBS_signatures_2018_03_28.csv
sigproextractor/data/vcftest/breast_genomes_all_indels.txt
sigproextractor/data/vcftest/breast_genomes_all_subs_simple_2.txt
new_sigproextractor-0.0.0.1.dist-info/METADATA
new_sigproextractor-0.0.0.1.dist-info/WHEEL
new_sigproextractor-0.0.0.1.dist-info/top_level.txt
new_sigproextractor-0.0.0.1.dist-info/RECORD
