Metadata-Version: 2.1
Name: new-sigproextractor
Version: 0.0.0.1
Summary: Extracts mutational signatures from mutational catalogues
Home-page: https://github.com/AlexandrovLab/SigProfilerExtractor.git
Author: S Mishu Ashiqul Islam
Author-email: m0islam@ucsd.edu
License: UCSD
Platform: UNKNOWN
Requires-Dist: matplotlib (>=2.2.2)
Requires-Dist: scipy (>=1.1.0)
Requires-Dist: numpy (>=1.14.4)
Requires-Dist: pandas (>=0.23.4)
Requires-Dist: nimfa (>=1.1.0)
Requires-Dist: SigProfilerMatrixGenerator (>=0.1.20)
Requires-Dist: sigProfilerPlotting (>=0.1.17)
Requires-Dist: pillow
Requires-Dist: statsmodels (>=0.9.0)
Requires-Dist: scikit-learn (>=0.20.2)
